rats/aml/__init__.py
rats/aml/__main__.py
rats/aml/_app.py
rats/aml/_configs.py
rats/aml/_request.py
rats/aml/_submission.py
rats/amlruntime/__init__.py
rats/amlruntime/_plugin.py
rats/amlruntime/_runtime.py
rats/amlruntime/py.typed
rats/ci/__init__.py
rats/ci/__main__.py
rats/ci/_app.py
rats/ci/py.typed
rats/docs/__init__.py
rats/docs/__main__.py
rats/docs/_app.py
rats/docs/py.typed
rats/ez/__init__.py
rats/ez/__main__.py
rats/ez/_app.py
rats/ez/py.typed
rats/projects/__init__.py
rats/projects/_component_tools.py
rats/projects/_container_images.py
rats/projects/_plugin.py
rats/projects/_project_tools.py
rats/projects/py.typed
rats_e2e/aml/__init__.py
rats_e2e/aml/basic/__init__.py
rats_e2e/aml/basic/_app.py
rats_e2e/aml/cli/__init__.py
rats_e2e/aml/cli/__main__.py
rats_e2e/aml/cli/_app.py
rats_resources/aml/__init__.py
rats_resources/aml/example-context.yaml
rats_resources/docs/__init__.py
rats_resources/docs/root-docs/css/extra.css
rats_resources/docs/root-docs/images/favicon.ico
rats_resources/docs/root-docs/images/logo.png
rats_devtools-0.16.0.dist-info/WHEEL
rats_devtools-0.16.0.dist-info/entry_points.txt
rats_devtools-0.16.0.dist-info/METADATA
rats_devtools-0.16.0.dist-info/RECORD
