Metadata-Version: 2.4
Name: rats-devtools
Version: 0.16.0
Summary: Rats Development Tools
Keywords: pipelines,machine learning,research
Author: Elon Portugaly, Javier Zazo, Lorenzo Pisani
Author-email: Elon Portugaly <elonp@microsoft.com>, Javier Zazo <javierzazo@microsoft.com>, Lorenzo Pisani <lopisani@microsoft.com>
License-Expression: MIT
Requires-Dist: rats-apps
Requires-Dist: click
Requires-Dist: toml
Requires-Dist: azure-ai-ml
Requires-Dist: azure-identity
Requires-Python: >=3.10, <4.0
Project-URL: repository, https://github.com/microsoft/rats
Project-URL: documentation, https://microsoft.github.io/rats
